Metadata-Version: 2.1
Name: qaoverpapers
Version: 0.0.1
Summary: qa over papers
Author: mcgrady164
Author-email: mcgrady150318@163.com
